gcode_metadata/__init__.py
gcode_metadata/metadata.py
gcode_metadata/py.typed
py_gcode_metadata-0.2.0.data/data/share/doc/gcode-metadata/ChangeLog
py_gcode_metadata-0.2.0.data/data/share/doc/gcode-metadata/LICENSE
py_gcode_metadata-0.2.0.data/data/share/doc/gcode-metadata/README.md
py_gcode_metadata-0.2.0.dist-info/LICENSE
py_gcode_metadata-0.2.0.dist-info/METADATA
py_gcode_metadata-0.2.0.dist-info/WHEEL
py_gcode_metadata-0.2.0.dist-info/top_level.txt
py_gcode_metadata-0.2.0.dist-info/RECORD
